idmycve/__init__.py
idmycve/idmycve.py
idmycve-0.2.6.dist-info/licenses/LICENSE
idmycve-0.2.6.dist-info/METADATA
idmycve-0.2.6.dist-info/WHEEL
idmycve-0.2.6.dist-info/entry_points.txt
idmycve-0.2.6.dist-info/top_level.txt
idmycve-0.2.6.dist-info/RECORD
